webhook_server_container/__init__.py
webhook_server_container/app.py
webhook_server_container/libs/__init__.py
webhook_server_container/libs/github_api.py
webhook_server_container/libs/sonar_qube.py
webhook_server_container/utils/__init__.py
webhook_server_container/utils/constants.py
webhook_server_container/utils/dockerhub_rate_limit.py
webhook_server_container/utils/github_repository_settings.py
webhook_server_container/utils/helpers.py
webhook_server_container/utils/sonar_qube.py
webhook_server_container/utils/webhook.py
github_webhook_server-0.0.0.dist-info/LICENSE
github_webhook_server-0.0.0.dist-info/METADATA
github_webhook_server-0.0.0.dist-info/WHEEL
github_webhook_server-0.0.0.dist-info/RECORD
