Metadata-Version: 2.1
Name: github-webhook-server
Version: 0.0.0
Summary: A webhook server to manage Github reposotories and pull requests.
Home-page: https://github.com/myakove/github-webhook-server
License: Apache-2.0
Author: Meni Yakove
Author-email: myakove@gmail.com
Requires-Python: >=3.8,<4.0
Classifier: License :: OSI Approved :: Apache Software License
Classifier: Operating System :: OS Independent
Classifier: Programming Language :: Python :: 3
Classifier: Programming Language :: Python :: 3.8
Classifier: Programming Language :: Python :: 3.9
Classifier: Programming Language :: Python :: 3.10
Classifier: Programming Language :: Python :: 3.11
Requires-Dist: build (>=0.10.0,<0.11.0)
Requires-Dist: flask (>=2.3.2,<3.0.0)
Requires-Dist: poetry-dynamic-versioning[plugin] (>=0.25.0,<0.26.0)
Requires-Dist: pygithub (>=1.59.0,<2.0.0)
Requires-Dist: python-sonarqube-api (>=2.0.4,<3.0.0)
Requires-Dist: pyyaml (>=6.0,<7.0)
Requires-Dist: shortuuid (>=1.0.11,<2.0.0)
Requires-Dist: twine (>=4.0.2,<5.0.0)
Project-URL: Bug Tracker, https://github.com/myakove/github-webhook-server/issues
Project-URL: Download, https://quay.io/repository/myakove/github-webhook-server
Project-URL: Repository, https://github.com/myakove/github-webhook-server
